lektor_markdown_image_attrs.py
lektor_markdown_image_attrs-0.2.1.dist-info/METADATA
lektor_markdown_image_attrs-0.2.1.dist-info/WHEEL
lektor_markdown_image_attrs-0.2.1.dist-info/entry_points.txt
lektor_markdown_image_attrs-0.2.1.dist-info/licenses/LICENSE
lektor_markdown_image_attrs-0.2.1.dist-info/RECORD
