Metadata-Version: 2.1
Name: lektor-markdown-image-attrs
Version: 0.2.1
Summary: Extend Lektor’s Markdown syntax to allow setting arbitrary HTML attributes on images and links.
Project-URL: Homepage, https://github.com/dairiki/lektor-markdown-image-attrs
Author-email: Jeff Dairiki <dairiki@dairiki.org>
License-File: LICENSE
Keywords: Lektor,attributes,html,image,markdown,plugin,style
Classifier: Development Status :: 4 - Beta
Classifier: Environment :: Plugins
Classifier: Environment :: Web Environment
Classifier: Framework :: Lektor
Classifier: Intended Audience :: Developers
Classifier: License :: OSI Approved :: MIT License
Classifier: Programming Language :: Python :: 3
Classifier: Programming Language :: Python :: 3.7
Classifier: Programming Language :: Python :: 3.8
Classifier: Programming Language :: Python :: 3.9
Classifier: Programming Language :: Python :: 3.10
Classifier: Topic :: Text Processing :: Markup :: HTML
Classifier: Topic :: Text Processing :: Markup :: Markdown
Requires-Python: >=3.7
